distro2sbom/__init__.py
distro2sbom/cli.py
distro2sbom/test.py
distro2sbom/version.py
distro2sbom/distrobuilder/__init__.py
distro2sbom/distrobuilder/distrobuilder.py
distro2sbom/distrobuilder/dpkgbuilder.py
distro2sbom/distrobuilder/freebsdbuilder.py
distro2sbom/distrobuilder/rpmbuilder.py
distro2sbom/distrobuilder/windowsbuilder.py
distro2sbom-0.6.0.dist-info/LICENSE
distro2sbom-0.6.0.dist-info/METADATA
distro2sbom-0.6.0.dist-info/WHEEL
distro2sbom-0.6.0.dist-info/entry_points.txt
distro2sbom-0.6.0.dist-info/top_level.txt
distro2sbom-0.6.0.dist-info/RECORD
